{"word": "automatyzowa\u0107 si\u0119", "translations": ["\u0430\u0432\u0442\u043e\u043c\u0430\u0442\u0438\u0437\u0438\u0440\u043e\u0432\u0430\u0442\u044c\u0441\u044f"], "conj": {"present": {"polish_form": "Czas tera\u017aniejszy", "russian_form": "\u041d\u0430\u0441\u0442\u043e\u044f\u0449\u0435\u0435 \u0432\u0440\u0435\u043c\u044f", "conj": {"ja": "automatyzuj\u0119 si\u0119", "ty": "automatyzujesz si\u0119", "on/ona/ono": "automatyzuje si\u0119", "my": "automatyzujemy si\u0119", "wy": "automatyzujecie si\u0119", "oni/one": "automatyzuj\u0105 si\u0119"}}, "past": {"polish_form": "Czas przesz\u0142y", "russian_form": "\u041f\u0440\u043e\u0448\u043b\u043e\u0435 \u0432\u0440\u0435\u043c\u044f", "conj": {"ja (m)": "automatyzowa\u0142em si\u0119", "ja (f)": "automatyzowa\u0142am si\u0119", "ty (m)": "automatyzowa\u0142e\u015b si\u0119", "ty (f)": "automatyzowa\u0142a\u015b si\u0119", "on": "automatyzowa\u0142 si\u0119", "ona": "automatyzowa\u0142a si\u0119", "ono": "automatyzowa\u0142o si\u0119", "my (m)": "automatyzowali\u015bmy si\u0119", "my (f)": "automatyzowa\u0142y\u015bmy si\u0119", "wy (m)": "automatyzowali\u015bcie si\u0119", "wy (f)": "automatyzowa\u0142y\u015bcie si\u0119", "oni": "automatyzowali si\u0119", "one": "automatyzowa\u0142y si\u0119"}}, "future_perfect": {"polish_form": "Czas przysz\u0142y z\u0142o\u017cony", "russian_form": "\u0411\u0443\u0434\u0443\u0449\u0435\u0435 \u0441\u043e\u0432\u0435\u0440\u0448\u0451\u043d\u043d\u043e\u0435 \u0432\u0440\u0435\u043c\u044f", "conj": {"ja (m)": "b\u0119d\u0119 si\u0119 automatyzowa\u0142", "ja (f)": "b\u0119d\u0119 si\u0119 automatyzowa\u0142a", "ty (m)": "b\u0119dziesz si\u0119 automatyzowa\u0142", "ty (f)": "b\u0119dziesz si\u0119 automatyzowa\u0142a", "on": "b\u0119dzie si\u0119 automatyzowa\u0142", "ona": "b\u0119dzie si\u0119 automatyzowa\u0142a", "ono": "b\u0119dzie si\u0119 automatyzowa\u0142o", "my (m)": "b\u0119dziemy si\u0119 automatyzowali", "my (f)": "b\u0119dziemy si\u0119 automatyzowa\u0142y", "wy (m)": "b\u0119dziecie si\u0119 automatyzowali", "wy (f)": "b\u0119dziecie si\u0119 automatyzowa\u0142y", "oni": "b\u0119d\u0105 si\u0119 automatyzowali", "one": "b\u0119d\u0105 si\u0119 automatyzowa\u0142y"}}, "subjunctive": {"polish_form": "Tryb przypuszczaj\u0105cy", "russian_form": "\u0421\u043e\u0441\u043b\u0430\u0433\u0430\u0442\u0435\u043b\u044c\u043d\u043e\u0435 \u043d\u0430\u043a\u043b\u043e\u043d\u0435\u043d\u0438\u0435", "conj": {"ja (m)": "automatyzowa\u0142bym si\u0119", "ja (f)": "automatyzowa\u0142abym si\u0119", "ty (m)": "automatyzowa\u0142by\u015b si\u0119", "ty (f)": "automatyzowa\u0142aby\u015b si\u0119", "on": "automatyzowa\u0142by si\u0119", "ona": "automatyzowa\u0142aby si\u0119", "ono": "automatyzowa\u0142oby si\u0119", "my (m)": "automatyzowaliby\u015bmy si\u0119", "my (f)": "automatyzowa\u0142yby\u015bmy si\u0119", "wy (m)": "automatyzowaliby\u015bcie si\u0119", "wy (f)": "automatyzowa\u0142yby\u015bcie si\u0119", "oni": "automatyzowaliby si\u0119", "one": "automatyzowa\u0142yby si\u0119"}}, "imperative": {"polish_form": "Tryb rozkazuj\u0105cy", "russian_form": "\u0418\u043c\u043f\u0435\u0440\u0430\u0442\u0438\u0432", "conj": {"ty": "automatyzuj si\u0119", "on/ona/ono": "niech si\u0119 automatyzuje", "my": "automatyzujmy si\u0119", "wy": "automatyzujcie si\u0119", "oni/one": "niech si\u0119 automatyzuje"}}}}