{"word": "klatkowa\u0107", "translations": [], "conj": {"present": {"polish_form": "Czas tera\u017aniejszy", "russian_form": "\u041d\u0430\u0441\u0442\u043e\u044f\u0449\u0435\u0435 \u0432\u0440\u0435\u043c\u044f", "conj": {"ja": "klatkuj\u0119", "ty": "klatkujesz", "on/ona/ono": "klatkuje", "my": "klatkujemy", "wy": "klatkujecie", "oni/one": "klatkuj\u0105"}}, "past": {"polish_form": "Czas przesz\u0142y", "russian_form": "\u041f\u0440\u043e\u0448\u043b\u043e\u0435 \u0432\u0440\u0435\u043c\u044f", "conj": {"ja (m)": "klatkowa\u0142em", "ja (f)": "klatkowa\u0142am", "ty (m)": "klatkowa\u0142e\u015b", "ty (f)": "klatkowa\u0142a\u015b", "on": "klatkowa\u0142", "ona": "klatkowa\u0142a", "ono": "klatkowa\u0142o", "my (m)": "klatkowali\u015bmy", "my (f)": "klatkowa\u0142y\u015bmy", "wy (m)": "klatkowali\u015bcie", "wy (f)": "klatkowa\u0142y\u015bcie", "oni": "klatkowali", "one": "klatkowa\u0142y"}}, "future_perfect": {"polish_form": "Czas przysz\u0142y z\u0142o\u017cony", "russian_form": "\u0411\u0443\u0434\u0443\u0449\u0435\u0435 \u0441\u043e\u0432\u0435\u0440\u0448\u0451\u043d\u043d\u043e\u0435 \u0432\u0440\u0435\u043c\u044f", "conj": {"ja (m)": "b\u0119d\u0119 klatkowa\u0142", "ja (f)": "b\u0119d\u0119 klatkowa\u0142a", "ty (m)": "b\u0119dziesz klatkowa\u0142", "ty (f)": "b\u0119dziesz klatkowa\u0142a", "on": "b\u0119dzie klatkowa\u0142", "ona": "b\u0119dzie klatkowa\u0142a", "ono": "b\u0119dzie klatkowa\u0142o", "my (m)": "b\u0119dziemy klatkowali", "my (f)": "b\u0119dziemy klatkowa\u0142y", "wy (m)": "b\u0119dziecie klatkowali", "wy (f)": "b\u0119dziecie klatkowa\u0142y", "oni": "b\u0119d\u0105 klatkowali", "one": "b\u0119d\u0105 klatkowa\u0142y"}}, "subjunctive": {"polish_form": "Tryb przypuszczaj\u0105cy", "russian_form": "\u0421\u043e\u0441\u043b\u0430\u0433\u0430\u0442\u0435\u043b\u044c\u043d\u043e\u0435 \u043d\u0430\u043a\u043b\u043e\u043d\u0435\u043d\u0438\u0435", "conj": {"ja (m)": "klatkowa\u0142bym", "ja (f)": "klatkowa\u0142abym", "ty (m)": "klatkowa\u0142by\u015b", "ty (f)": "klatkowa\u0142aby\u015b", "on": "klatkowa\u0142by", "ona": "klatkowa\u0142aby", "ono": "klatkowa\u0142oby", "my (m)": "klatkowaliby\u015bmy", "my (f)": "klatkowa\u0142yby\u015bmy", "wy (m)": "klatkowaliby\u015bcie", "wy (f)": "klatkowa\u0142yby\u015bcie", "oni": "klatkowaliby", "one": "klatkowa\u0142yby"}}, "imperative": {"polish_form": "Tryb rozkazuj\u0105cy", "russian_form": "\u0418\u043c\u043f\u0435\u0440\u0430\u0442\u0438\u0432", "conj": {"ty": "klatkuj", "on/ona/ono": "niech klatkuje", "my": "klatkujmy", "wy": "klatkujcie", "oni/one": "niech klatkuj\u0105"}}}}