{"word": "obs\u0142ugiwa\u0107", "translations": ["\u043e\u0431\u0441\u043b\u0443\u0436\u0438\u0432\u0430\u0442\u044c", "\u043f\u0440\u0438\u0441\u043b\u0443\u0436\u0438\u0432\u0430\u0442\u044c"], "conj": {"present": {"polish_form": "Czas tera\u017aniejszy", "russian_form": "\u041d\u0430\u0441\u0442\u043e\u044f\u0449\u0435\u0435 \u0432\u0440\u0435\u043c\u044f", "conj": {"ja": "obs\u0142uguj\u0119", "ty": "obs\u0142ugujesz", "on/ona/ono": "obs\u0142uguje", "my": "obs\u0142ugujemy", "wy": "obs\u0142ugujecie", "oni/one": "obs\u0142uguj\u0105"}}, "past": {"polish_form": "Czas przesz\u0142y", "russian_form": "\u041f\u0440\u043e\u0448\u043b\u043e\u0435 \u0432\u0440\u0435\u043c\u044f", "conj": {"ja (m)": "obs\u0142ugiwa\u0142em", "ja (f)": "obs\u0142ugiwa\u0142am", "ty (m)": "obs\u0142ugiwa\u0142e\u015b", "ty (f)": "obs\u0142ugiwa\u0142a\u015b", "on": "obs\u0142ugiwa\u0142", "ona": "obs\u0142ugiwa\u0142a", "ono": "obs\u0142ugiwa\u0142o", "my (m)": "obs\u0142ugiwali\u015bmy", "my (f)": "obs\u0142ugiwa\u0142y\u015bmy", "wy (m)": "obs\u0142ugiwali\u015bcie", "wy (f)": "obs\u0142ugiwa\u0142y\u015bcie", "oni": "obs\u0142ugiwali", "one": "obs\u0142ugiwa\u0142y"}}, "future_perfect": {"polish_form": "Czas przysz\u0142y z\u0142o\u017cony", "russian_form": "\u0411\u0443\u0434\u0443\u0449\u0435\u0435 \u0441\u043e\u0432\u0435\u0440\u0448\u0451\u043d\u043d\u043e\u0435 \u0432\u0440\u0435\u043c\u044f", "conj": {"ja (m)": "b\u0119d\u0119 obs\u0142ugiwa\u0142", "ja (f)": "b\u0119d\u0119 obs\u0142ugiwa\u0142a", "ty (m)": "b\u0119dziesz obs\u0142ugiwa\u0142", "ty (f)": "b\u0119dziesz obs\u0142ugiwa\u0142a", "on": "b\u0119dzie obs\u0142ugiwa\u0142", "ona": "b\u0119dzie obs\u0142ugiwa\u0142a", "ono": "b\u0119dzie obs\u0142ugiwa\u0142o", "my (m)": "b\u0119dziemy obs\u0142ugiwali", "my (f)": "b\u0119dziemy obs\u0142ugiwa\u0142y", "wy (m)": "b\u0119dziecie obs\u0142ugiwali", "wy (f)": "b\u0119dziecie obs\u0142ugiwa\u0142y", "oni": "b\u0119d\u0105 obs\u0142ugiwali", "one": "b\u0119d\u0105 obs\u0142ugiwa\u0142y"}}, "subjunctive": {"polish_form": "Tryb przypuszczaj\u0105cy", "russian_form": "\u0421\u043e\u0441\u043b\u0430\u0433\u0430\u0442\u0435\u043b\u044c\u043d\u043e\u0435 \u043d\u0430\u043a\u043b\u043e\u043d\u0435\u043d\u0438\u0435", "conj": {"ja (m)": "obs\u0142ugiwa\u0142bym", "ja (f)": "obs\u0142ugiwa\u0142abym", "ty (m)": "obs\u0142ugiwa\u0142by\u015b", "ty (f)": "obs\u0142ugiwa\u0142aby\u015b", "on": "obs\u0142ugiwa\u0142by", "ona": "obs\u0142ugiwa\u0142aby", "ono": "obs\u0142ugiwa\u0142oby", "my (m)": "obs\u0142ugiwaliby\u015bmy", "my (f)": "obs\u0142ugiwa\u0142yby\u015bmy", "wy (m)": "obs\u0142ugiwaliby\u015bcie", "wy (f)": "obs\u0142ugiwa\u0142yby\u015bcie", "oni": "obs\u0142ugiwaliby", "one": "obs\u0142ugiwa\u0142yby"}}, "imperative": {"polish_form": "Tryb rozkazuj\u0105cy", "russian_form": "\u0418\u043c\u043f\u0435\u0440\u0430\u0442\u0438\u0432", "conj": {"ty": "obs\u0142uguj", "on/ona/ono": "niech obs\u0142uguje", "my": "obs\u0142ugujcie", "wy": "obs\u0142ugujmy", "oni/one": "niech obs\u0142uguj\u0105"}}}}