{"word": "rachowa\u0107", "translations": ["\u043f\u0435\u0440\u0435\u0441\u0447\u0438\u0442\u044b\u0432\u0430\u0442\u044c"], "conj": {"present": {"polish_form": "Czas tera\u017aniejszy", "russian_form": "\u041d\u0430\u0441\u0442\u043e\u044f\u0449\u0435\u0435 \u0432\u0440\u0435\u043c\u044f", "conj": {"ja": "rachuj\u0119", "ty": "rachujesz", "on/ona/ono": "rachuje", "my": "rachujemy", "wy": "rachujecie", "oni/one": "rachuj\u0105"}}, "past": {"polish_form": "Czas przesz\u0142y", "russian_form": "\u041f\u0440\u043e\u0448\u043b\u043e\u0435 \u0432\u0440\u0435\u043c\u044f", "conj": {"ja (m)": "rachowa\u0142em", "ja (f)": "rachowa\u0142am", "ty (m)": "rachowa\u0142e\u015b", "ty (f)": "rachowa\u0142a\u015b", "on": "rachowa\u0142", "ona": "rachowa\u0142a", "ono": "rachowa\u0142o", "my (m)": "rachowali\u015bmy", "my (f)": "rachowa\u0142y\u015bmy", "wy (m)": "rachowali\u015bcie", "wy (f)": "rachowa\u0142y\u015bcie", "oni": "rachowali", "one": "rachowa\u0142y"}}, "future_perfect": {"polish_form": "Czas przysz\u0142y z\u0142o\u017cony", "russian_form": "\u0411\u0443\u0434\u0443\u0449\u0435\u0435 \u0441\u043e\u0432\u0435\u0440\u0448\u0451\u043d\u043d\u043e\u0435 \u0432\u0440\u0435\u043c\u044f", "conj": {"ja (m)": "b\u0119d\u0119 rachowa\u0142", "ja (f)": "b\u0119d\u0119 rachowa\u0142a", "ty (m)": "b\u0119dziesz rachowa\u0142", "ty (f)": "b\u0119dziesz rachowa\u0142a", "on": "b\u0119dzie rachowa\u0142", "ona": "b\u0119dzie rachowa\u0142a", "ono": "b\u0119dzie rachowa\u0142o", "my (m)": "b\u0119dziemy rachowali", "my (f)": "b\u0119dziemy rachowa\u0142y", "wy (m)": "b\u0119dziecie rachowali", "wy (f)": "b\u0119dziecie rachowa\u0142y", "oni": "b\u0119d\u0105 rachowali", "one": "b\u0119d\u0105 rachowa\u0142y"}}, "subjunctive": {"polish_form": "Tryb przypuszczaj\u0105cy", "russian_form": "\u0421\u043e\u0441\u043b\u0430\u0433\u0430\u0442\u0435\u043b\u044c\u043d\u043e\u0435 \u043d\u0430\u043a\u043b\u043e\u043d\u0435\u043d\u0438\u0435", "conj": {"ja (m)": "rachowa\u0142bym", "ja (f)": "rachowa\u0142abym", "ty (m)": "rachowa\u0142by\u015b", "ty (f)": "rachowa\u0142aby\u015b", "on": "rachowa\u0142by", "ona": "rachowa\u0142aby", "ono": "rachowa\u0142oby", "my (m)": "rachowaliby\u015bmy", "my (f)": "rachowa\u0142yby\u015bmy", "wy (m)": "rachowaliby\u015bcie", "wy (f)": "rachowa\u0142yby\u015bcie", "oni": "rachowaliby", "one": "rachowa\u0142yby"}}, "imperative": {"polish_form": "Tryb rozkazuj\u0105cy", "russian_form": "\u0418\u043c\u043f\u0435\u0440\u0430\u0442\u0438\u0432", "conj": {"ty": "rachuj", "on/ona/ono": "niech rachuje", "my": "rachujmy", "wy": "rachujcie", "oni/one": "niech rachuj\u0105"}}}}