{"word": "udr\u0119czy\u0107", "translations": ["\u0443\u0449\u0435\u043c\u0438\u0442\u044c"], "conj": {"present_perfect": {"polish_form": "Czas przysz\u0142y prosty", "russian_form": "\u041d\u0430\u0441\u0442\u043e\u044f\u0449\u0435\u0435 \u0441\u0440\u043e\u0432\u0435\u0440\u0448\u0451\u043d\u043d\u043e\u0435 \u0432\u0440\u0435\u043c\u044f", "conj": {"ja": "udr\u0119cz\u0119", "ty": "udr\u0119czysz", "on/ona/ono": "udr\u0119czy", "my": "udr\u0119czymy", "wy": "udr\u0119czycie", "oni/one": "udr\u0119cz\u0105"}}, "past": {"polish_form": "Czas przesz\u0142y", "russian_form": "\u041f\u0440\u043e\u0448\u043b\u043e\u0435 \u0432\u0440\u0435\u043c\u044f", "conj": {"ja (m)": "udr\u0119czy\u0142em", "ja (f)": "udr\u0119czy\u0142am", "ty (m)": "udr\u0119czy\u0142e\u015b", "ty (f)": "udr\u0119czy\u0142a\u015b", "on": "udr\u0119czy\u0142", "ona": "udr\u0119czy\u0142a", "ono": "udr\u0119czy\u0142o", "my (m)": "udr\u0119czyli\u015bmy", "my (f)": "udr\u0119czy\u0142y\u015bmy", "wy (m)": "udr\u0119czyli\u015bcie", "wy (f)": "udr\u0119czy\u0142y\u015bcie", "oni": "udr\u0119czyli", "one": "udr\u0119czy\u0142y"}}, "subjunctive": {"polish_form": "Tryb przypuszczaj\u0105cy", "russian_form": "\u0421\u043e\u0441\u043b\u0430\u0433\u0430\u0442\u0435\u043b\u044c\u043d\u043e\u0435 \u043d\u0430\u043a\u043b\u043e\u043d\u0435\u043d\u0438\u0435", "conj": {"ja (m)": "udr\u0119czy\u0142bym", "ja (f)": "udr\u0119czy\u0142abym", "ty (m)": "udr\u0119czy\u0142by\u015b", "ty (f)": "udr\u0119czy\u0142aby\u015b", "on": "udr\u0119czy\u0142by", "ona": "udr\u0119czy\u0142aby", "ono": "udr\u0119czy\u0142oby", "my (m)": "udr\u0119czyliby\u015bmy", "my (f)": "udr\u0119czy\u0142yby\u015bmy", "wy (m)": "udr\u0119czyliby\u015bcie", "wy (f)": "udr\u0119czy\u0142yby\u015bcie", "oni": "udr\u0119czyliby", "one": "udr\u0119czy\u0142yby"}}, "imperative": {"polish_form": "Tryb rozkazuj\u0105cy", "russian_form": "\u0418\u043c\u043f\u0435\u0440\u0430\u0442\u0438\u0432", "conj": {"ty": "udr\u0119cz", "on/ona/ono": "niech udr\u0119czy", "my": "udr\u0119czmy", "wy": "udr\u0119czcie", "oni/one": "niech udr\u0119cz\u0105"}}}}