{"word": "wyrychtowa\u0107", "translations": [], "conj": {"present_perfect": {"polish_form": "Czas przysz\u0142y prosty", "russian_form": "\u041d\u0430\u0441\u0442\u043e\u044f\u0449\u0435\u0435 \u0441\u0440\u043e\u0432\u0435\u0440\u0448\u0451\u043d\u043d\u043e\u0435 \u0432\u0440\u0435\u043c\u044f", "conj": {"ja": "wyrychtuj\u0119", "ty": "wyrychtujesz", "on/ona/ono": "wyrychtuje", "my": "wyrychtujemy", "wy": "wyrychtujecie", "oni/one": "wyrychtuj\u0105"}}, "past": {"polish_form": "Czas przesz\u0142y", "russian_form": "\u041f\u0440\u043e\u0448\u043b\u043e\u0435 \u0432\u0440\u0435\u043c\u044f", "conj": {"ja (m)": "wyrychtowa\u0142em", "ja (f)": "wyrychtowa\u0142am", "ty (m)": "wyrychtowa\u0142e\u015b", "ty (f)": "wyrychtowa\u0142a\u015b", "on": "wyrychtowa\u0142", "ona": "wyrychtowa\u0142a", "ono": "wyrychtowa\u0142o", "my (m)": "wyrychtowali\u015bmy", "my (f)": "wyrychtowa\u0142y\u015bmy", "wy (m)": "wyrychtowali\u015bcie", "wy (f)": "wyrychtowa\u0142y\u015bcie", "oni": "wyrychtowali", "one": "wyrychtowa\u0142y"}}, "subjunctive": {"polish_form": "Tryb przypuszczaj\u0105cy", "russian_form": "\u0421\u043e\u0441\u043b\u0430\u0433\u0430\u0442\u0435\u043b\u044c\u043d\u043e\u0435 \u043d\u0430\u043a\u043b\u043e\u043d\u0435\u043d\u0438\u0435", "conj": {"ja (m)": "wyrychtowa\u0142bym", "ja (f)": "wyrychtowa\u0142abym", "ty (m)": "wyrychtowa\u0142by\u015b", "ty (f)": "wyrychtowa\u0142aby\u015b", "on": "wyrychtowa\u0142by", "ona": "wyrychtowa\u0142aby", "ono": "wyrychtowa\u0142oby", "my (m)": "wyrychtowaliby\u015bmy", "my (f)": "wyrychtowa\u0142yby\u015bmy", "wy (m)": "wyrychtowaliby\u015bcie", "wy (f)": "wyrychtowa\u0142yby\u015bcie", "oni": "wyrychtowaliby", "one": "wyrychtowa\u0142yby"}}, "imperative": {"polish_form": "Tryb rozkazuj\u0105cy", "russian_form": "\u0418\u043c\u043f\u0435\u0440\u0430\u0442\u0438\u0432", "conj": {"ty": "wyrychtuj", "on/ona/ono": "niech wyrychtuje", "my": "wyrychtujmy", "wy": "wyrychtujcie", "oni/one": "niech wyrychtuj\u0105"}}}}