{"word": "zdarzy\u0107", "translations": ["\u043f\u0440\u043e\u0438\u0437\u043e\u0439\u0442\u0438"], "conj": {"present_perfect": {"polish_form": "Czas przysz\u0142y prosty", "russian_form": "\u041d\u0430\u0441\u0442\u043e\u044f\u0449\u0435\u0435 \u0441\u0440\u043e\u0432\u0435\u0440\u0448\u0451\u043d\u043d\u043e\u0435 \u0432\u0440\u0435\u043c\u044f", "conj": {"ja": "zdarz\u0119", "ty": "zdarzysz", "on/ona/ono": "zdarzy", "my": "zdarzymy", "wy": "zdarzycie", "oni/one": "zdarz\u0105"}}, "past": {"polish_form": "Czas przesz\u0142y", "russian_form": "\u041f\u0440\u043e\u0448\u043b\u043e\u0435 \u0432\u0440\u0435\u043c\u044f", "conj": {"ja (m)": "zdarzy\u0142em", "ja (f)": "zdarzy\u0142am", "ty (m)": "zdarzy\u0142e\u015b", "ty (f)": "zdarzy\u0142a\u015b", "on": "zdarzy\u0142", "ona": "zdarzy\u0142a", "ono": "zdarzy\u0142o", "my (m)": "zdarzyli\u015bmy", "my (f)": "zdarzy\u0142y\u015bmy", "wy (m)": "zdarzyli\u015bcie", "wy (f)": "zdarzy\u0142y\u015bcie", "oni": "zdarzyli", "one": "zdarzy\u0142y"}}, "subjunctive": {"polish_form": "Tryb przypuszczaj\u0105cy", "russian_form": "\u0421\u043e\u0441\u043b\u0430\u0433\u0430\u0442\u0435\u043b\u044c\u043d\u043e\u0435 \u043d\u0430\u043a\u043b\u043e\u043d\u0435\u043d\u0438\u0435", "conj": {"ja (m)": "zdarzy\u0142bym", "ja (f)": "zdarzy\u0142abym", "ty (m)": "zdarzy\u0142by\u015b", "ty (f)": "zdarzy\u0142aby\u015b", "on": "zdarzy\u0142by", "ona": "zdarzy\u0142aby", "ono": "zdarzy\u0142oby", "my (m)": "zdarzyliby\u015bmy", "my (f)": "zdarzy\u0142yby\u015bmy", "wy (m)": "zdarzyliby\u015bcie", "wy (f)": "zdarzy\u0142yby\u015bcie", "oni": "zdarzyliby", "one": "zdarzy\u0142yby"}}, "imperative": {"polish_form": "Tryb rozkazuj\u0105cy", "russian_form": "\u0418\u043c\u043f\u0435\u0440\u0430\u0442\u0438\u0432", "conj": {"ty": "zdarz", "on/ona/ono": "niech zdarzy", "my": "zdarzmy", "wy": "zdarzcie", "oni/one": "niech zdarz\u0105"}}}}