{"word": "zr\u00f3wnowa\u017cy\u0107", "translations": ["\u0443\u0440\u0430\u0432\u043d\u043e\u0432\u0435\u0441\u0438\u0442\u044c", "\u043e\u043f\u0440\u0430\u0432\u0434\u0430\u0442\u044c"], "conj": {"present_perfect": {"polish_form": "Czas przysz\u0142y prosty", "russian_form": "\u041d\u0430\u0441\u0442\u043e\u044f\u0449\u0435\u0435 \u0441\u0440\u043e\u0432\u0435\u0440\u0448\u0451\u043d\u043d\u043e\u0435 \u0432\u0440\u0435\u043c\u044f", "conj": {"ja": "zr\u00f3wnowa\u017c\u0119", "ty": "zr\u00f3wnowa\u017cysz", "on/ona/ono": "zr\u00f3wnowa\u017cy", "my": "zr\u00f3wnowa\u017cymy", "wy": "zr\u00f3wnowa\u017cycie", "oni/one": "zr\u00f3wnowa\u017c\u0105"}}, "past": {"polish_form": "Czas przesz\u0142y", "russian_form": "\u041f\u0440\u043e\u0448\u043b\u043e\u0435 \u0432\u0440\u0435\u043c\u044f", "conj": {"ja (m)": "zr\u00f3wnowa\u017cy\u0142em", "ja (f)": "zr\u00f3wnowa\u017cy\u0142am", "ty (m)": "zr\u00f3wnowa\u017cy\u0142e\u015b", "ty (f)": "zr\u00f3wnowa\u017cy\u0142a\u015b", "on": "zr\u00f3wnowa\u017cy\u0142", "ona": "zr\u00f3wnowa\u017cy\u0142a", "ono": "zr\u00f3wnowa\u017cy\u0142o", "my (m)": "zr\u00f3wnowa\u017cyli\u015bmy", "my (f)": "zr\u00f3wnowa\u017cy\u0142y\u015bmy", "wy (m)": "zr\u00f3wnowa\u017cyli\u015bcie", "wy (f)": "zr\u00f3wnowa\u017cy\u0142y\u015bcie", "oni": "zr\u00f3wnowa\u017cyli", "one": "zr\u00f3wnowa\u017cy\u0142y"}}, "subjunctive": {"polish_form": "Tryb przypuszczaj\u0105cy", "russian_form": "\u0421\u043e\u0441\u043b\u0430\u0433\u0430\u0442\u0435\u043b\u044c\u043d\u043e\u0435 \u043d\u0430\u043a\u043b\u043e\u043d\u0435\u043d\u0438\u0435", "conj": {"ja (m)": "zr\u00f3wnowa\u017cy\u0142bym", "ja (f)": "zr\u00f3wnowa\u017cy\u0142abym", "ty (m)": "zr\u00f3wnowa\u017cy\u0142by\u015b", "ty (f)": "zr\u00f3wnowa\u017cy\u0142aby\u015b", "on": "zr\u00f3wnowa\u017cy\u0142by", "ona": "zr\u00f3wnowa\u017cy\u0142aby", "ono": "zr\u00f3wnowa\u017cy\u0142oby", "my (m)": "zr\u00f3wnowa\u017cyliby\u015bmy", "my (f)": "zr\u00f3wnowa\u017cy\u0142yby\u015bmy", "wy (m)": "zr\u00f3wnowa\u017cyliby\u015bcie", "wy (f)": "zr\u00f3wnowa\u017cy\u0142yby\u015bcie", "oni": "zr\u00f3wnowa\u017cyliby", "one": "zr\u00f3wnowa\u017cy\u0142yby"}}, "imperative": {"polish_form": "Tryb rozkazuj\u0105cy", "russian_form": "\u0418\u043c\u043f\u0435\u0440\u0430\u0442\u0438\u0432", "conj": {"ty": "zr\u00f3wnowa\u017c", "on/ona/ono": "niech zr\u00f3wnowa\u017cy", "my": "zr\u00f3wnowa\u017cmy", "wy": "zr\u00f3wnowa\u017ccie", "oni/one": "niech zr\u00f3wnowa\u017c\u0105"}}}}